{
    "name": "Dicalcium Phosphate",
    "desc": "Dicalcium Phosphate is a combination of phosphorus and calcium. Dicalcium Phosphate is usually made by combining sulfuric or phosphoric acid with phosphate rock or other insoluble calcium phosphates. This mixture is then treated with calcium chloride to produce dibasic sodium phosphate.",
    "techs": "Dicalcium Phosphate appears in the form of a white powder. The prefix “di” in the name of Dicalcium Phosphate is formed because the compound formation consists in removing two parts from phosphoric acid.",
    "shelf": "The shelf life of Dicalcium Phosphate is 2 years.",
    "packaging": "Foodcom supplies its Business Partners with Dicalcium Phosphate in 25 kg bags or in Big Bags.",
    "applications": "Dicalcium Phosphate is a component of animal diets as a source of phosphorus and a feed corrector. Thanks to this mineral, food rations meet the needs of animals, improving growth and fertility.
Phosphorus is essential, ie. in the process of ATP, the synthesis of nucleic acids, and bone formation."
}